[
  {
    "borsa": "binance",
    "sembol": "BTCUSDT",
    "zaman": "2026-03-12 16:58:07",
    "alis_emirleri": [
      [
        70383.5,
        0.03551
      ],
      [
        70380.49,
        0.0042
      ],
      [
        70350.81,
        0.07541
      ],
      [
        70350.8,
        0.00991
      ],
      [
        70326.39,
        0.14217
      ],
      [
        70223.85,
        0.01473
      ],
      [
        70223.84,
        0.65494
      ],
      [
        70182.6,
        0.10521
      ],
      [
        70162.6,
        0.11052
      ],
      [
        70112.32,
        0.00258
      ]
    ],
    "satis_emirleri": [
      [
        70416.7,
        0.03549
      ],
      [
        70420.42,
        0.00772
      ],
      [
        70446.24,
        0.35397
      ],
      [
        70464.7,
        0.00017
      ],
      [
        70491.23,
        0.00603
      ],
      [
        70491.25,
        0.14184
      ],
      [
        70515.17,
        0.0186
      ],
      [
        70574.57,
        0.0003
      ],
      [
        70576.97,
        0.70833
      ],
      [
        70583.86,
        0.06379
      ]
    ]
  },
  {
    "borsa": "coinbase",
    "sembol": "BTC-USD",
    "zaman": "2026-03-12 16:59:13",
    "alis_emirleri": [
      [
        70399.94,
        1.09254298
      ],
      [
        70398.88,
        0.10430455
      ],
      [
        70397.47,
        0.00071022
      ],
      [
        70396.0,
        0.014
      ],
      [
        70394.61,
        0.38968125
      ],
      [
        70394.0,
        0.014
      ],
      [
        70393.09,
        0.00088779
      ],
      [
        70390.11,
        0.00150198
      ],
      [
        70390.0,
        0.001
      ],
      [
        70389.37,
        0.11644509
      ]
    ],
    "satis_emirleri": [
      [
        70399.95,
        0.16961173
      ],
      [
        70400.73,
        0.04261319
      ],
      [
        70401.01,
        0.01420434
      ],
      [
        70402.0,
        0.014
      ],
      [
        70402.42,
        0.00071022
      ],
      [
        70404.0,
        0.014
      ],
      [
        70404.79,
        0.06098314
      ],
      [
        70405.0,
        0.001
      ],
      [
        70406.0,
        0.014
      ],
      [
        70406.51,
        0.06177312
      ]
    ]
  },
  {
    "borsa": "okx",
    "sembol": "BTC-USDT-SWAP",
    "zaman": "2026-03-12 16:59:32",
    "alis_emirleri": [
      [
        70333.9,
        2193.0
      ],
      [
        70333.8,
        0.04
      ],
      [
        70333.0,
        0.15
      ],
      [
        70332.8,
        0.01
      ],
      [
        70332.7,
        14.8
      ],
      [
        70332.5,
        0.02
      ],
      [
        70332.4,
        7.03
      ],
      [
        70332.3,
        0.01
      ],
      [
        70332.1,
        0.01
      ],
      [
        70332.0,
        6.87
      ]
    ],
    "satis_emirleri": [
      [
        70334.0,
        99.41
      ],
      [
        70334.1,
        1.38
      ],
      [
        70334.3,
        0.42
      ],
      [
        70334.4,
        0.07
      ],
      [
        70334.5,
        5.1
      ],
      [
        70334.6,
        0.03
      ],
      [
        70334.7,
        0.07
      ],
      [
        70334.8,
        3.34
      ],
      [
        70335.0,
        0.05
      ],
      [
        70335.1,
        0.05
      ]
    ]
  },
  {
    "borsa": "mexc",
    "sembol": "BTCUSDT",
    "zaman": "2026-03-12 17:00:12",
    "alis_emirleri": [
      [
        70403.7,
        0.00015048
      ],
      [
        70403.68,
        0.080424
      ],
      [
        70403.67,
        0.00142975
      ],
      [
        70403.47,
        0.08635689
      ],
      [
        70403.15,
        0.00130656
      ],
      [
        70403.14,
        0.00136499
      ],
      [
        70403.02,
        0.00152977
      ],
      [
        70403.01,
        0.00146628
      ],
      [
        70402.75,
        0.0014909
      ],
      [
        70402.74,
        0.009144
      ]
    ],
    "satis_emirleri": [
      [
        70403.84,
        0.502814
      ],
      [
        70405.42,
        0.08635689
      ],
      [
        70405.61,
        0.502814
      ],
      [
        70405.78,
        0.08635689
      ],
      [
        70405.96,
        2.53589354
      ],
      [
        70406.14,
        0.08635689
      ],
      [
        70407.08,
        0.0018
      ],
      [
        70407.29,
        0.120789
      ],
      [
        70407.38,
        0.502814
      ],
      [
        70408.64,
        0.00128087
      ]
    ]
  },
  {
    "borsa": "gateio",
    "sembol": "BTC_USDT",
    "zaman": "2026-03-12 17:00:30",
    "alis_emirleri": [
      [
        70411.9,
        0.463532
      ],
      [
        70410.8,
        0.000852
      ],
      [
        70410.7,
        8.5e-05
      ],
      [
        70408.7,
        0.16
      ],
      [
        70408.6,
        0.136484
      ],
      [
        70408.5,
        0.19896
      ],
      [
        70407.2,
        8.5e-05
      ],
      [
        70406.2,
        0.284927
      ],
      [
        70405.9,
        0.002
      ],
      [
        70405.8,
        0.088952
      ]
    ],
    "satis_emirleri": [
      [
        70412.0,
        0.256529
      ],
      [
        70412.7,
        0.015562
      ],
      [
        70412.8,
        0.050715
      ],
      [
        70414.8,
        0.00142
      ],
      [
        70417.5,
        0.00061
      ],
      [
        70418.8,
        0.14117
      ],
      [
        70418.9,
        0.16
      ],
      [
        70419.0,
        0.033503
      ],
      [
        70419.2,
        0.284428
      ],
      [
        70421.2,
        8.5e-05
      ]
    ]
  },
  {
    "borsa": "kucoin",
    "sembol": "BTC-USDT",
    "zaman": "2026-03-12 17:00:47",
    "alis_emirleri": [
      [
        70440.6,
        0.9467469
      ],
      [
        70440.5,
        0.02839271
      ],
      [
        70438.8,
        0.00283823
      ],
      [
        70435.3,
        0.24933887
      ],
      [
        70435.2,
        0.56765384
      ],
      [
        70435.1,
        0.26765225
      ],
      [
        70433.5,
        0.00435401
      ],
      [
        70432.0,
        0.0656259
      ],
      [
        70431.9,
        0.12765225
      ],
      [
        70431.7,
        0.0922
      ]
    ],
    "satis_emirleri": [
      [
        70440.7,
        0.02503066
      ],
      [
        70442.3,
        0.02840192
      ],
      [
        70447.5,
        0.00638774
      ],
      [
        70448.2,
        0.06496547
      ],
      [
        70448.9,
        0.0922
      ],
      [
        70449.3,
        0.02840063
      ],
      [
        70452.3,
        0.06392334
      ],
      [
        70453.0,
        0.01
      ],
      [
        70453.5,
        0.02154598
      ],
      [
        70454.7,
        0.01
      ]
    ]
  }
]