[
  {
    "borsa": "binance",
    "sembol": "BTCUSDT",
    "zaman": "2025-10-01 16:23:54",
    "alis_emirleri": [
      [
        117660.0,
        0.00036
      ],
      [
        117413.22,
        0.00024
      ],
      [
        117413.2,
        0.01065
      ],
      [
        117413.18,
        0.00862
      ],
      [
        117413.17,
        0.00483
      ],
      [
        117413.16,
        0.01056
      ],
      [
        117413.06,
        0.2198
      ],
      [
        117412.23,
        0.00076
      ],
      [
        117399.98,
        0.00743
      ],
      [
        117285.0,
        0.25616
      ]
    ],
    "satis_emirleri": [
      [
        117664.71,
        0.10075
      ],
      [
        117677.08,
        0.0001
      ],
      [
        117687.7,
        0.00026
      ],
      [
        117711.16,
        0.00096
      ],
      [
        117722.09,
        0.00434
      ],
      [
        117741.04,
        0.03342
      ],
      [
        117741.06,
        0.12
      ],
      [
        117741.08,
        0.00078
      ],
      [
        117754.24,
        0.00164
      ],
      [
        117763.09,
        0.0044
      ]
    ]
  },
  {
    "borsa": "coinbase",
    "sembol": "BTC-USD",
    "zaman": "2025-10-01 16:24:33",
    "alis_emirleri": [
      [
        117812.63,
        0.31536194
      ],
      [
        117811.75,
        0.00679
      ],
      [
        117810.01,
        0.00169764
      ],
      [
        117810.0,
        0.0429
      ],
      [
        117809.68,
        0.0254648
      ],
      [
        117809.39,
        0.00679
      ],
      [
        117808.09,
        0.21299828
      ],
      [
        117808.08,
        0.01975069
      ],
      [
        117808.01,
        0.0424203
      ],
      [
        117808.0,
        0.0429
      ]
    ],
    "satis_emirleri": [
      [
        117812.64,
        0.0393084
      ],
      [
        117812.66,
        0.01801164
      ],
      [
        117813.86,
        0.02546389
      ],
      [
        117814.0,
        0.0429
      ],
      [
        117815.04,
        8.49e-06
      ],
      [
        117815.59,
        0.02546352
      ],
      [
        117816.0,
        0.0429
      ],
      [
        117817.92,
        0.0025563
      ],
      [
        117818.0,
        0.0429
      ],
      [
        117818.56,
        0.014565
      ]
    ]
  },
  {
    "borsa": "okx",
    "sembol": "BTC-USDT-SWAP",
    "zaman": "2025-10-01 16:24:37",
    "alis_emirleri": [
      [
        117703.0,
        893.41
      ],
      [
        117702.9,
        0.29
      ],
      [
        117702.8,
        26.11
      ],
      [
        117702.7,
        0.01
      ],
      [
        117700.8,
        0.01
      ],
      [
        117700.7,
        0.01
      ],
      [
        117700.6,
        0.01
      ],
      [
        117700.0,
        0.02
      ],
      [
        117699.8,
        0.01
      ],
      [
        117699.6,
        23.48
      ]
    ],
    "satis_emirleri": [
      [
        117703.1,
        342.79
      ],
      [
        117703.2,
        0.02
      ],
      [
        117704.0,
        1.59
      ],
      [
        117705.0,
        1.09
      ],
      [
        117705.1,
        3.4
      ],
      [
        117705.5,
        4.18
      ],
      [
        117705.6,
        73.99
      ],
      [
        117705.7,
        131.12
      ],
      [
        117706.0,
        1.09
      ],
      [
        117706.4,
        0.01
      ]
    ]
  },
  {
    "borsa": "bitget",
    "sembol": "BTCUSDT_SPBL",
    "zaman": "2025-10-01 16:25:12",
    "alis_emirleri": [
      [
        117735.29,
        1.577223
      ],
      [
        117735.19,
        0.159918
      ],
      [
        117734.44,
        0.05
      ],
      [
        117734.07,
        0.001683
      ],
      [
        117733.1,
        0.02
      ],
      [
        117732.7,
        0.954824
      ],
      [
        117732.69,
        0.002123
      ],
      [
        117730.87,
        0.05
      ],
      [
        117730.27,
        0.007638
      ],
      [
        117730.01,
        0.466991
      ]
    ],
    "satis_emirleri": [
      [
        117735.3,
        1.445366
      ],
      [
        117735.72,
        0.000849
      ],
      [
        117736.36,
        3.443784
      ],
      [
        117737.96,
        0.05
      ],
      [
        117739.8,
        0.279602
      ],
      [
        117739.81,
        0.765894
      ],
      [
        117740.23,
        0.002123
      ],
      [
        117740.42,
        0.02
      ],
      [
        117742.21,
        0.00166
      ],
      [
        117742.96,
        0.05
      ]
    ]
  },
  {
    "borsa": "mexc",
    "sembol": "BTCUSDT",
    "zaman": "2025-10-01 16:25:14",
    "alis_emirleri": [
      [
        117740.65,
        4.0127
      ],
      [
        117740.64,
        0.09518743
      ],
      [
        117740.58,
        0.09340033
      ],
      [
        117740.39,
        0.08586039
      ],
      [
        117740.38,
        0.08773242
      ],
      [
        117740.37,
        0.08745919
      ],
      [
        117740.36,
        0.08624017
      ],
      [
        117740.21,
        0.09432586
      ],
      [
        117740.2,
        0.08891479
      ],
      [
        117740.19,
        0.08508109
      ]
    ],
    "satis_emirleri": [
      [
        117740.66,
        3.69638922
      ],
      [
        117740.67,
        0.08775995
      ],
      [
        117740.74,
        0.0870601
      ],
      [
        117741.24,
        0.09701662
      ],
      [
        117741.25,
        0.0933442
      ],
      [
        117741.91,
        0.09666504
      ],
      [
        117741.92,
        0.08525772
      ],
      [
        117741.93,
        0.08578353
      ],
      [
        117742.14,
        0.08927461
      ],
      [
        117742.32,
        0.09169832
      ]
    ]
  },
  {
    "borsa": "gateio",
    "sembol": "BTC_USDT",
    "zaman": "2025-10-01 16:25:34",
    "alis_emirleri": [
      [
        117745.4,
        2.07028
      ],
      [
        117744.6,
        0.039746
      ],
      [
        117744.5,
        0.141727
      ],
      [
        117742.3,
        0.005098
      ],
      [
        117740.0,
        0.03
      ],
      [
        117739.9,
        0.540419
      ],
      [
        117738.9,
        0.062992
      ],
      [
        117738.8,
        0.342989
      ],
      [
        117735.3,
        0.04015
      ],
      [
        117735.0,
        0.179398
      ]
    ],
    "satis_emirleri": [
      [
        117745.5,
        0.397908
      ],
      [
        117746.1,
        0.015434
      ],
      [
        117746.5,
        0.006
      ],
      [
        117746.6,
        0.01699
      ],
      [
        117747.3,
        0.0048
      ],
      [
        117750.0,
        0.00017
      ],
      [
        117750.7,
        0.04015
      ],
      [
        117752.0,
        0.001724
      ],
      [
        117754.2,
        0.002
      ],
      [
        117754.4,
        0.000126
      ]
    ]
  },
  {
    "borsa": "kucoin",
    "sembol": "BTC-USDT",
    "zaman": "2025-10-01 16:25:52",
    "alis_emirleri": [
      [
        117739.6,
        1.2786195
      ],
      [
        117739.5,
        0.19244724
      ],
      [
        117739.4,
        0.16
      ],
      [
        117739.3,
        0.02546392
      ],
      [
        117738.9,
        0.02546401
      ],
      [
        117738.4,
        0.16
      ],
      [
        117738.3,
        0.04767041
      ],
      [
        117738.0,
        0.004
      ],
      [
        117737.9,
        0.004
      ],
      [
        117737.8,
        0.004
      ]
    ],
    "satis_emirleri": [
      [
        117739.7,
        0.17524154
      ],
      [
        117741.0,
        0.0001
      ],
      [
        117741.9,
        0.00203544
      ],
      [
        117742.0,
        0.0001
      ],
      [
        117742.3,
        0.004
      ],
      [
        117742.4,
        0.02547937
      ],
      [
        117742.6,
        0.004
      ],
      [
        117742.8,
        0.004
      ],
      [
        117743.0,
        0.0041
      ],
      [
        117743.1,
        0.17
      ]
    ]
  }
]