[
  {
    "borsa": "binance",
    "sembol": "BTCUSDT",
    "zaman": "2026-02-28 01:54:59",
    "alis_emirleri": [
      [
        65795.89,
        0.00784
      ],
      [
        65795.78,
        0.11151
      ],
      [
        65794.25,
        0.04595
      ],
      [
        65794.15,
        0.04027
      ],
      [
        65791.36,
        0.0152
      ],
      [
        65758.8,
        0.00018
      ],
      [
        65729.64,
        0.15214
      ],
      [
        65676.41,
        0.11936
      ],
      [
        65605.06,
        0.02901
      ],
      [
        65605.05,
        0.76218
      ]
    ],
    "satis_emirleri": [
      [
        65817.59,
        0.01519
      ],
      [
        65817.8,
        0.04
      ],
      [
        65828.7,
        0.00017
      ],
      [
        65828.83,
        0.00815
      ],
      [
        65840.09,
        0.37887
      ],
      [
        65840.85,
        0.08895
      ],
      [
        65875.05,
        0.15181
      ],
      [
        66000.0,
        5e-05
      ],
      [
        66003.64,
        0.75758
      ],
      [
        66005.64,
        0.11995
      ]
    ]
  },
  {
    "borsa": "coinbase",
    "sembol": "BTC-USD",
    "zaman": "2026-02-28 01:55:37",
    "alis_emirleri": [
      [
        65811.32,
        0.05095585
      ],
      [
        65810.33,
        0.02283772
      ],
      [
        65810.0,
        0.03934497
      ],
      [
        65809.01,
        0.06948745
      ],
      [
        65808.48,
        1.7e-05
      ],
      [
        65808.0,
        0.0393
      ],
      [
        65807.8,
        0.00148312
      ],
      [
        65806.38,
        0.00030389
      ],
      [
        65806.01,
        0.07682677
      ],
      [
        65806.0,
        0.0393
      ]
    ],
    "satis_emirleri": [
      [
        65811.33,
        0.16315397
      ],
      [
        65812.32,
        0.02279209
      ],
      [
        65812.8,
        0.11793115
      ],
      [
        65812.81,
        0.1519461
      ],
      [
        65813.47,
        0.06382339
      ],
      [
        65813.48,
        0.04559352
      ],
      [
        65813.64,
        0.00075974
      ],
      [
        65815.42,
        0.0009497
      ],
      [
        65816.0,
        0.0393
      ],
      [
        65816.09,
        0.02
      ]
    ]
  },
  {
    "borsa": "okx",
    "sembol": "BTC-USDT-SWAP",
    "zaman": "2026-02-28 01:55:56",
    "alis_emirleri": [
      [
        65782.7,
        386.99
      ],
      [
        65782.6,
        0.02
      ],
      [
        65782.4,
        0.01
      ],
      [
        65782.1,
        0.04
      ],
      [
        65782.0,
        0.01
      ],
      [
        65781.5,
        0.77
      ],
      [
        65781.3,
        0.01
      ],
      [
        65781.2,
        0.03
      ],
      [
        65781.0,
        0.77
      ],
      [
        65780.7,
        0.01
      ]
    ],
    "satis_emirleri": [
      [
        65782.8,
        472.61
      ],
      [
        65782.9,
        0.01
      ],
      [
        65783.0,
        0.77
      ],
      [
        65783.2,
        0.01
      ],
      [
        65783.3,
        0.15
      ],
      [
        65783.4,
        0.01
      ],
      [
        65783.5,
        0.79
      ],
      [
        65783.6,
        22.8
      ],
      [
        65783.9,
        0.02
      ],
      [
        65784.0,
        9.81
      ]
    ]
  },
  {
    "borsa": "mexc",
    "sembol": "BTCUSDT",
    "zaman": "2026-02-28 01:56:18",
    "alis_emirleri": [
      [
        65819.93,
        0.99115699
      ],
      [
        65819.92,
        0.00322394
      ],
      [
        65819.27,
        0.00305
      ],
      [
        65818.84,
        0.00304641
      ],
      [
        65818.19,
        0.00302828
      ],
      [
        65817.85,
        0.0031884
      ],
      [
        65817.84,
        0.06722
      ],
      [
        65817.83,
        0.0124
      ],
      [
        65817.8,
        0.00336619
      ],
      [
        65817.79,
        0.13149
      ]
    ],
    "satis_emirleri": [
      [
        65819.94,
        5.41746773
      ],
      [
        65819.95,
        0.00296329
      ],
      [
        65820.15,
        0.00319654
      ],
      [
        65820.19,
        0.00361
      ],
      [
        65820.6,
        0.00337495
      ],
      [
        65820.73,
        0.00298103
      ],
      [
        65820.8,
        0.00290513
      ],
      [
        65820.89,
        0.00316473
      ],
      [
        65821.06,
        0.00289
      ],
      [
        65821.07,
        0.02016
      ]
    ]
  },
  {
    "borsa": "gateio",
    "sembol": "BTC_USDT",
    "zaman": "2026-02-28 01:56:22",
    "alis_emirleri": [
      [
        65813.8,
        0.585149
      ],
      [
        65813.1,
        0.112138
      ],
      [
        65813.0,
        0.0426
      ],
      [
        65812.7,
        0.000607
      ],
      [
        65812.1,
        0.16
      ],
      [
        65812.0,
        0.2026
      ],
      [
        65811.9,
        0.17131
      ],
      [
        65811.8,
        0.160607
      ],
      [
        65811.7,
        0.004935
      ],
      [
        65811.1,
        0.16
      ]
    ],
    "satis_emirleri": [
      [
        65813.9,
        0.614573
      ],
      [
        65814.0,
        0.0426
      ],
      [
        65814.1,
        0.002
      ],
      [
        65814.5,
        0.094066
      ],
      [
        65814.6,
        0.205695
      ],
      [
        65814.8,
        0.000303
      ],
      [
        65815.0,
        0.0426
      ],
      [
        65815.2,
        0.009755
      ],
      [
        65815.3,
        0.16
      ],
      [
        65815.4,
        0.000607
      ]
    ]
  },
  {
    "borsa": "kucoin",
    "sembol": "BTC-USDT",
    "zaman": "2026-02-28 01:56:43",
    "alis_emirleri": [
      [
        65818.1,
        0.25580156
      ],
      [
        65818.0,
        0.1119852
      ],
      [
        65817.9,
        0.00761356
      ],
      [
        65817.5,
        0.06582484
      ],
      [
        65817.4,
        0.00867313
      ],
      [
        65817.1,
        0.04558402
      ],
      [
        65816.9,
        0.03860457
      ],
      [
        65816.7,
        0.02276396
      ],
      [
        65816.6,
        0.0479324
      ],
      [
        65816.5,
        0.00036929
      ]
    ],
    "satis_emirleri": [
      [
        65818.2,
        0.08764839
      ],
      [
        65818.3,
        0.04565917
      ],
      [
        65819.9,
        0.0187465
      ],
      [
        65820.3,
        0.02200823
      ],
      [
        65820.4,
        0.01069583
      ],
      [
        65820.5,
        0.09123801
      ],
      [
        65820.6,
        0.01677951
      ],
      [
        65821.4,
        0.01913119
      ],
      [
        65821.5,
        0.05180067
      ],
      [
        65821.6,
        0.01352941
      ]
    ]
  }
]